Workbook
Name aporte: APP!$D$17
Name patrimonio: APP!$D$20
Name qtd_anos: APP!$D$18
Name rendimento_carteira: APP!$D$13
Name salario: APP!$D$12
Name sugestao_investimento: APP!$D$14
Name taxa_mensal: APP!$D$19

Sheet APP
B11: CONFIGURAÇÕES
B12: Salário | D12: 1621
B13: Rendimento Carteira | D13: 0.006
B14: Sugestão de Investimento (30%) | D14: =D12*30% -> 486.3
B16: INVESTIMENTO MENSAL
B17: Quanto investir por mês? | D17: 300
B18: Por Quantos Anos? | D18: 7
B19: Taxa de Rendimento mensal? | D19: 0.01079
B20: Patrimônio acumulado? | D20: =FV(taxa_mensal,qtd_anos*12,aporte*-1) -> 40685.11
B21: Dividendo Mensais? | D21: =patrimonio*rendimento_carteira -> 244.11066
B23: Cenários | D23: Dividendo
A24: 2 | B24: Quantos em 2 anos? | C24: =FV($D$19,$A24*12,$D$17*-1) -> 8168.2882 | D24: =C24*rendimento_carteira -> 49.009729
A25: 5 | B25: Quantos em 5 anos? | C25: =FV($D$19,$A25*12,$D$17*-1) -> 25133.074 | D25: =C25*rendimento_carteira -> 150.79845
A26: 10 | B26: Quantos em 10 anos? | C26: =FV($D$19,$A26*12,$D$17*-1) -> 72985.264 | D26: =C26*rendimento_carteira -> 437.91158
A27: 20 | B27: Quantos em 20 anos? | C27: =FV($D$19,$A27*12,$D$17*-1) -> 337559.52 | D27: =C27*rendimento_carteira -> 2025.3571
A28: 30 | B28: Quantos em 30 anos? | C28: =FV($D$19,$A28*12,$D$17*-1) -> 1296650.9 | D28: =C28*rendimento_carteira -> 7779.9054
B31: PERFIL | C31: Conservador
B32: VALOR A SER INVESTIDO POR MÊS | C32: =aporte -> 300
B34: TIPO DE FII | C34: Percentual Sugerido | D34: Valores
B35: PAPEL | C35: =VLOOKUP($C$31&"-"&B35,CHAVE!$A:$D,4,FALSE) -> 0.3 | D35: =C35*$C$32 -> 90
B36: TIJOLO | C36: =VLOOKUP($C$31&"-"&B36,CHAVE!$A:$D,4,FALSE) -> 0.5 | D36: =C36*$C$32 -> 150
B37: HÍBRIDOS | C37: =VLOOKUP($C$31&"-"&B37,CHAVE!$A:$D,4,FALSE) -> 0.1 | D37: =C37*$C$32 -> 30
B38: FOFs | C38: =VLOOKUP($C$31&"-"&B38,CHAVE!$A:$D,4,FALSE) -> 0.1 | D38: =C38*$C$32 -> 30
B39: DESENVOLVIMENTO | C39: =VLOOKUP($C$31&"-"&B39,CHAVE!$A:$D,4,FALSE) -> 0 | D39: =C39*$C$32 -> 0
B40: HOTELARIAS | C40: =VLOOKUP($C$31&"-"&B40,CHAVE!$A:$D,4,FALSE) -> 0 | D40: =C40*$C$32 -> 0
D41: =SUM(D35:D40) -> 300

Sheet CHAVE
A2: CHAVE | B2: PERFIL | C2: TIPO DE FII | D2: % | G2: %
A3: =B3&"-"&C3 -> Conservador-PAPEL | B3: Conservador | C3: PAPEL | D3: 0.3 | F3: Moderado-TIJOLO | G3: =VLOOKUP(F3,$A:$D,4,FALSE) -> 0.35
A4: =B4&"-"&C4 -> Conservador-TIJOLO | B4: Conservador | C4: TIJOLO | D4: 0.5
A5: =B5&"-"&C5 -> Conservador-HÍBRIDOS | B5: Conservador | C5: HÍBRIDOS | D5: 0.1
A6: =B6&"-"&C6 -> Conservador-FOFs | B6: Conservador | C6: FOFs | D6: 0.1
A7: =B7&"-"&C7 -> Conservador-DESENVOLVIMENTO | B7: Conservador | C7: DESENVOLVIMENTO | D7: 0
A8: =B8&"-"&C8 -> Conservador-HOTELARIAS | B8: Conservador | C8: HOTELARIAS | D8: 0
A9: =B9&"-"&C9 -> Moderado-PAPEL | B9: Moderado | C9: PAPEL | D9: 0.32
A10: =B10&"-"&C10 -> Moderado-TIJOLO | B10: Moderado | C10: TIJOLO | D10: 0.35
A11: =B11&"-"&C11 -> Moderado-HÍBRIDOS | B11: Moderado | C11: HÍBRIDOS | D11: 0.08
A12: =B12&"-"&C12 -> Moderado-FOFs | B12: Moderado | C12: FOFs | D12: 0.05
A13: =B13&"-"&C13 -> Moderado-DESENVOLVIMENTO | B13: Moderado | C13: DESENVOLVIMENTO | D13: 0.1
A14: =B14&"-"&C14 -> Moderado-HOTELARIAS | B14: Moderado | C14: HOTELARIAS | D14: 0.1
A15: =B15&"-"&C15 -> Agressivo-PAPEL | B15: Agressivo | C15: PAPEL | D15: 0.5
... A20: =B20&"-"&C20 -> Agressivo-HOTELARIAS | B20: Agressivo | C20: HOTELARIAS | D20: 0.1
